CHANGES.txt
LICENSE.txt
MANIFEST.in
README.txt
bootstrap.py
buildout.cfg
setup.py
src/p01/__init__.py
src/p01.vocabulary.cache.egg-info/PKG-INFO
src/p01.vocabulary.cache.egg-info/SOURCES.txt
src/p01.vocabulary.cache.egg-info/dependency_links.txt
src/p01.vocabulary.cache.egg-info/namespace_packages.txt
src/p01.vocabulary.cache.egg-info/not-zip-safe
src/p01.vocabulary.cache.egg-info/requires.txt
src/p01.vocabulary.cache.egg-info/top_level.txt
src/p01/vocabulary/__init__.py
src/p01/vocabulary/cache/README.txt
src/p01/vocabulary/cache/__init__.py
src/p01/vocabulary/cache/interfaces.py
src/p01/vocabulary/cache/testing.py
src/p01/vocabulary/cache/tests.py
src/p01/vocabulary/cache/vocabulary.py