Metadata-Version: 1.0
Name: p01.vocabulary.cache
Version: 0.5.0
Summary: Legacy data supported and i18n sorted vocabularies for Zope3
Home-page: http://pypi.python.org/pypi/p01.vocabulary.cache
Author: Roger Ineichen, Projekt01 GmbH
Author-email: dev@projekt01.ch
License: ZPL 2.1
Keywords: zope3 z3c p01 vocabulary language sorted i18n cache
Platform: UNKNOWN
Classifier: Development Status :: 4 - Beta
Classifier: Environment :: Web Environment
Classifier: Intended Audience :: Developers
Classifier: License :: OSI Approved :: Zope Public License
Classifier: Programming Language :: Python
Classifier: Natural Language :: English
Classifier: Operating System :: OS Independent
Classifier: Topic :: Internet :: WWW/HTTP
Classifier: Framework :: Zope3
